Metadata-Version: 2.2
Name: django-iris
Version: 0.3.0
Summary: Django backend for InterSystems IRIS
Home-page: https://github.com/caretdev/django-iris
Maintainer: CaretDev
Maintainer-email: dmitry@caretdev.com
License: MIT
Project-URL: Source, https://github.com/caretdev/django-iris
Project-URL: Tracker, https://github.com/caretdev/django-iris/issues
Classifier: Development Status :: 5 - Production/Stable
Classifier: Framework :: Django
Classifier: Framework :: Django :: 5.0
Classifier: License :: OSI Approved :: MIT License
Classifier: Operating System :: OS Independent
Classifier: Programming Language :: Python
Classifier: Programming Language :: Python :: 3
Classifier: Programming Language :: Python :: 3.8
Classifier: Programming Language :: Python :: 3.9
Classifier: Programming Language :: Python :: 3.10
Classifier: Programming Language :: Python :: 3.11
Classifier: Programming Language :: Python :: 3.12
Requires-Python: >=3.8
License-File: LICENSE
